MANIFEST.in
README.md
setup.py
telegram_messages_dump/__init__.py
telegram_messages_dump/__main__.py
telegram_messages_dump/chat_dump_metadata.py
telegram_messages_dump/chat_dump_settings.py
telegram_messages_dump/exceptions.py
telegram_messages_dump/exporter_context.py
telegram_messages_dump/run.py
telegram_messages_dump/telegram_dumper.py
telegram_messages_dump/utils.py
telegram_messages_dump.egg-info/PKG-INFO
telegram_messages_dump.egg-info/SOURCES.txt
telegram_messages_dump.egg-info/dependency_links.txt
telegram_messages_dump.egg-info/entry_points.txt
telegram_messages_dump.egg-info/requires.txt
telegram_messages_dump.egg-info/top_level.txt
telegram_messages_dump/exporters/__init__.py
telegram_messages_dump/exporters/common.py
telegram_messages_dump/exporters/csv.py
telegram_messages_dump/exporters/jsonl.py
telegram_messages_dump/exporters/text.py