Metadata-Version: 2.1
Name: telegram-messages-dump
Version: 0.4
Summary: Telegram Messages Dump console utility.
Home-page: https://github.com/Kosat/telegram-messages-dump
Author: Kostya Kravets
Author-email: kostikkv@gmail.com
License: MIT
Download-URL: https://github.com/Kosat/telegram-messages-dump/releases
Platform: UNKNOWN
Classifier: Environment :: Console
Classifier: Intended Audience :: Developers
Classifier: Intended Audience :: System Administrators
Classifier: License :: OSI Approved :: MIT License
Classifier: Programming Language :: Python
Classifier: Programming Language :: Python :: 3
